LICENSE
MANIFEST.in
README.md
setup.py
pdcopyist/__init__.py
pdcopyist/main.py
pdcopyist/startup_linux.sh
pdcopyist/startup_win.bat
pdcopyist.egg-info/PKG-INFO
pdcopyist.egg-info/SOURCES.txt
pdcopyist.egg-info/dependency_links.txt
pdcopyist.egg-info/entry_points.txt
pdcopyist.egg-info/requires.txt
pdcopyist.egg-info/top_level.txt
pdcopyist/src/__init__.py
pdcopyist/src/controllers/command_controller.py
pdcopyist/src/controllers/common.py
pdcopyist/src/controllers/cusFuns_controller.py
pdcopyist/src/controllers/groupby_controller.py
pdcopyist/src/controllers/loaddata_controller.py
pdcopyist/src/controllers/loaddata_model.py
pdcopyist/src/controllers/query_controller.py
pdcopyist/src/controllers/table_controller.py
pdcopyist/src/core/CodeFormatter.py
pdcopyist/src/core/Commander.py
pdcopyist/src/core/MethodCall.py
pdcopyist/src/core/Proxy.py
pdcopyist/src/core/Statement.py
pdcopyist/src/core/UIArgs.py
pdcopyist/src/core/__init__.py
pdcopyist/src/cusFuns/__init__.py
pdcopyist/src/cusFuns/columnNameChanger/index.py
pdcopyist/src/cusFuns/columnRemover/index.py
pdcopyist/src/cusFuns/columnStrReplace/index.py
pdcopyist/src/cusFuns/core/DecoratorFuns.py
pdcopyist/src/cusFuns/core/FunsPool.py
pdcopyist/src/cusFuns/core/UIModl.py
pdcopyist/src/cusFuns/core/__init__.py
pdcopyist/src/cusFuns/exportFile/index_csv.py
pdcopyist/src/cusFuns/exportFile/index_excel.py
pdcopyist/src/cusFuns/exportFile/index_feather.py
pdcopyist/src/cusFuns/typeChanger/index.py
pdcopyist/src/dataModel/pandasCmd.py
pdcopyist/src/helper/utils.py
pdcopyist/web/static/css/app.3a302805.css
pdcopyist/web/static/css/chunk-vendors.7d0c439b.css
pdcopyist/web/static/img/dataWhere.9bcc2ab0.gif
pdcopyist/web/static/js/app.4ad7346f.js
pdcopyist/web/static/js/app.4ad7346f.js.map
pdcopyist/web/static/js/chunk-vendors.e2a6e84d.js
pdcopyist/web/static/js/chunk-vendors.e2a6e84d.js.map
pdcopyist/web/templates/index.html